localrun/__init__.py
localrun/cli.py
localrun/server.py
localrun-1.1.2.dist-info/LICENSE
localrun-1.1.2.dist-info/METADATA
localrun-1.1.2.dist-info/WHEEL
localrun-1.1.2.dist-info/entry_points.txt
localrun-1.1.2.dist-info/top_level.txt
localrun-1.1.2.dist-info/RECORD
